webamon_cli/__init__.py
webamon_cli/__main__.py
webamon_cli/cli.py
webamon_cli/client.py
webamon_cli/config.py
webamon_cli/scans_fields.json
webamon_cli-0.2.3.dist-info/licenses/LICENSE
webamon_cli-0.2.3.dist-info/METADATA
webamon_cli-0.2.3.dist-info/WHEEL
webamon_cli-0.2.3.dist-info/entry_points.txt
webamon_cli-0.2.3.dist-info/top_level.txt
webamon_cli-0.2.3.dist-info/RECORD
