Metadata-Version: 2.4
Name: webamon-cli
Version: 0.2.3
Summary: Webamon Search CLI - The Google of Threat Intelligence.
Author-email: Webamon <info@webamon.com>
License-Expression: Apache-2.0
Project-URL: Homepage, https://webamon.com
Project-URL: Repository, https://github.com/webamon-org/webamon-cli
Project-URL: Bug Tracker, https://github.com/webamon-org/webamon-cli/issues
Project-URL: Documentation, https://github.com/webamon-org/webamon-cli#readme
Project-URL: Webamon Search, https://google.webamon.com
Keywords: webamon,threat-intelligence,osint,security,threat,hunting,cli,cybersecurity,search,intel
Classifier: Development Status :: 4 - Beta
Classifier: Intended Audience :: Developers
Classifier: Intended Audience :: Information Technology
Classifier: Intended Audience :: System Administrators
Classifier: Topic :: Security
Classifier: Topic :: Internet :: WWW/HTTP
Classifier: Topic :: System :: Networking :: Monitoring
Classifier: Topic :: Software Development :: Libraries :: Python Modules
Classifier: Environment :: Console
Classifier: Programming Language :: Python :: 3
Classifier: Programming Language :: Python :: 3.8
Classifier: Programming Language :: Python :: 3.9
Classifier: Programming Language :: Python :: 3.10
Classifier: Programming Language :: Python :: 3.11
Classifier: Programming Language :: Python :: 3.12
Requires-Python: >=3.8
License-File: LICENSE
Requires-Dist: click>=8.0.0
Requires-Dist: requests>=2.25.0
Requires-Dist: rich>=10.0.0
Requires-Dist: pydantic>=1.8.0
Dynamic: license-file
